[{
    "Tävling": "Herrar 1966",
    "Datum": "1966-07-17",
    "Sträcka": "3000",
    "Start": "62",
    "I mål": "62"
  },{"Placering":1,"Namn":"von holst, sven","Klubb/Ort":"SKK","Startnr":"null","Tid":"36:13.0"},
{"Placering":2,"Namn":"danielsson, tommy","Klubb/Ort":"SKK","Startnr":"null","Tid":"37:20.0"},
{"Placering":3,"Namn":"karlsson, rickard","Klubb/Ort":"Kiruna SS","Startnr":"null","Tid":"37:24.0"},
{"Placering":4,"Namn":"hänninen, erkki","Klubb/Ort":"Finland","Startnr":"null","Tid":"38:09.0"},
{"Placering":5,"Namn":"karlsson, per arne","Klubb/Ort":"SKK","Startnr":"null","Tid":"39:28.0"},
{"Placering":6,"Namn":"lindblom, benny","Klubb/Ort":"Norrköpings KK","Startnr":"null","Tid":"40:26.0"},
{"Placering":7,"Namn":"magnusson, göran","Klubb/Ort":"IF Elfsborg","Startnr":"null","Tid":"40:57.0"},
{"Placering":8,"Namn":"classon, torbjörn","Klubb/Ort":"SKK","Startnr":"null","Tid":"42:14.0"},
{"Placering":9,"Namn":"hansson, hans olov","Klubb/Ort":"Finspångs SS","Startnr":"null","Tid":"42:28.0"},
{"Placering":10,"Namn":"andersson, jörgen","Klubb/Ort":"IF Elfsborg","Startnr":"null","Tid":"42:45.0"},
{"Placering":11,"Namn":"ågren, anders","Klubb/Ort":"Sollefteå GI0F","Startnr":"null","Tid":"43:33.0"},
{"Placering":12,"Namn":"hasselberg, staffan","Klubb/Ort":"Sollefteå GI0F","Startnr":"null","Tid":"43:35.0"},
{"Placering":12,"Namn":"tivell, anders","Klubb/Ort":"IF Elfsborg","Startnr":"null","Tid":"43:35.0"},
{"Placering":14,"Namn":"karlsson, benny","Klubb/Ort":"SK Lore","Startnr":"null","Tid":"45:13.0"},
{"Placering":15,"Namn":"magnusson, lars","Klubb/Ort":"Finspångs SK","Startnr":"null","Tid":"45:30.0"},
{"Placering":16,"Namn":"paleski, ronnie","Klubb/Ort":"Stockholmspolisen","Startnr":"null","Tid":"46:02.0"},
{"Placering":17,"Namn":"larsson, bernt","Klubb/Ort":"Gränges Simsällskap","Startnr":"null","Tid":"46:17.0"},
{"Placering":18,"Namn":"nilsson, lars","Klubb/Ort":"Harads IF","Startnr":"null","Tid":"46:39.0"},
{"Placering":19,"Namn":"johansson, christer","Klubb/Ort":"IF Elfsborg","Startnr":"null","Tid":"47:12.0"},
{"Placering":20,"Namn":"andersson, lennart","Klubb/Ort":"SKK","Startnr":"null","Tid":"47:14.0"},
{"Placering":21,"Namn":"swedberg, sture","Klubb/Ort":"Örebro SS","Startnr":"null","Tid":"47:17.0"},
{"Placering":22,"Namn":"holmgren, bertil","Klubb/Ort":"Harnäs SS","Startnr":"null","Tid":"47:31.0"},
{"Placering":23,"Namn":"lundmark, sven","Klubb/Ort":"Borlänge Simsällskap","Startnr":"null","Tid":"48:35.0"},
{"Placering":24,"Namn":"marcussén, arne","Klubb/Ort":"Danmark","Startnr":"null","Tid":"49:08.0"},
{"Placering":25,"Namn":"lindh, leif","Klubb/Ort":"Hudiksvalls SS","Startnr":"null","Tid":"50:03.0"},
{"Placering":26,"Namn":"thunström, lennart","Klubb/Ort":"Hälsingborgs SS","Startnr":"null","Tid":"50:32.0"},
{"Placering":27,"Namn":"malm, kenneth","Klubb/Ort":"Finspångs SS","Startnr":"null","Tid":"52:21.0"},
{"Placering":28,"Namn":"waldén, göran b.","Klubb/Ort":"Hällefors AIF","Startnr":"null","Tid":"53:00.0"},
{"Placering":29,"Namn":"ståhlberg, esbjörn","Klubb/Ort":"Harnäs SS","Startnr":"null","Tid":"53:07.0"},
{"Placering":30,"Namn":"heinefeldt, freddy","Klubb/Ort":"SK Lore","Startnr":"null","Tid":"54:53.0"},
{"Placering":31,"Namn":"karlsson, lennart","Klubb/Ort":"SK Lore","Startnr":"null","Tid":"55:52.0"},
{"Placering":32,"Namn":"giliusson, kent","Klubb/Ort":"Grängesberg SS","Startnr":"null","Tid":"56:53.0"},
{"Placering":33,"Namn":"montelius, ragnar","Klubb/Ort":"Gagnef","Startnr":"null","Tid":"57:01.0"},
{"Placering":34,"Namn":"jansson, leif","Klubb/Ort":"SK Lore","Startnr":"null","Tid":"57:52.0"},
{"Placering":35,"Namn":"hultin, per","Klubb/Ort":"Gränges Simsällskap","Startnr":"null","Tid":"57:53.0"},
{"Placering":36,"Namn":"holmgren, sören","Klubb/Ort":"SK Lore","Startnr":"null","Tid":"58:58.0"},
{"Placering":37,"Namn":"bengtsson, bengt","Klubb/Ort":"Hudiksvalls SS","Startnr":"null","Tid":"59:23.0"},
{"Placering":37,"Namn":"larsson, bo","Klubb/Ort":"SK Lore","Startnr":"null","Tid":"59:23.0"},
{"Placering":39,"Namn":"larsson, lars","Klubb/Ort":"SK Lore","Startnr":"null","Tid":"59:26.0"},
{"Placering":39,"Namn":"lindström, tommy","Klubb/Ort":"SK Lore","Startnr":"null","Tid":"59:26.0"},
{"Placering":41,"Namn":"eriksson, stig","Klubb/Ort":"Lima IF","Startnr":"null","Tid":"00:00.0"},
{"Placering":42,"Namn":"johansson, olle","Klubb/Ort":"SK Lore","Startnr":"null","Tid":"02:08.0"},
{"Placering":43,"Namn":"broberg, göte","Klubb/Ort":"Orsa IF","Startnr":"null","Tid":"02:10.0"},
{"Placering":44,"Namn":"montelius, erik","Klubb/Ort":"Gagnef IF","Startnr":"null","Tid":"02:35.0"},
{"Placering":45,"Namn":"portström, sven","Klubb/Ort":"Hallsta IK","Startnr":"null","Tid":"03:38.0"},
{"Placering":46,"Namn":"marcussen, frode","Klubb/Ort":"Danmark","Startnr":"null","Tid":"04:47.0"},
{"Placering":47,"Namn":"andersson, hans","Klubb/Ort":"Finspångs SS","Startnr":"null","Tid":"05:50.0"},
{"Placering":47,"Namn":"meijer, tommy","Klubb/Ort":"Finspångs SS","Startnr":"null","Tid":"05:50.0"},
{"Placering":49,"Namn":"thornell, acke","Klubb/Ort":"SK Lore","Startnr":"null","Tid":"06:44.0"},
{"Placering":50,"Namn":"bergström, rolf","Klubb/Ort":"IFK Grängesberg","Startnr":"null","Tid":"06:58.0"},
{"Placering":51,"Namn":"paleski, krister","Klubb/Ort":"Stockholmspolisen","Startnr":"null","Tid":"08:47.0"},
{"Placering":52,"Namn":"karlsson, per","Klubb/Ort":"VAIK","Startnr":"null","Tid":"09:05.0"},
{"Placering":53,"Namn":"widman, ove","Klubb/Ort":"SK Lore","Startnr":"null","Tid":"09:35.0"},
{"Placering":54,"Namn":"forsblad, john","Klubb/Ort":"Sollefteå GIOF","Startnr":"null","Tid":"10:12.0"},
{"Placering":55,"Namn":"lövgren, lars","Klubb/Ort":"SK Lore","Startnr":"null","Tid":"11:46.0"},
{"Placering":56,"Namn":"gustafsson, sverre","Klubb/Ort":"Ludvika FFI","Startnr":"null","Tid":"13:08.0"},
{"Placering":57,"Namn":"sjöström, mats","Klubb/Ort":"Västervik","Startnr":"null","Tid":"15:23.0"},
{"Placering":58,"Namn":"karlsson, roger","Klubb/Ort":"SK Lore","Startnr":"null","Tid":"16:15.0"},
{"Placering":58,"Namn":"valfridsson, göran","Klubb/Ort":"Gränges Simsällskap","Startnr":"null","Tid":"16:15.0"},
{"Placering":60,"Namn":"gustavsson, bo","Klubb/Ort":"SK Lore","Startnr":"null","Tid":"16:17.0"},
{"Placering":60,"Namn":"karlsson, tage","Klubb/Ort":"SK Lore","Startnr":"null","Tid":"16:17.0"},
{"Placering":62,"Namn":"håkansson, lennart","Klubb/Ort":"SAS IF","Startnr":"null","Tid":"45:21.0"}]