[{
    "Tävling": "Herrar 1962",
    "Datum": "1962-06-01",
    "Sträcka": "3000",
    "Start": "35",
    "I mål": "35"
  },{"Placering":1,"Namn":"ekman, sten","Klubb/Ort":"Tunafors SK","Startnr":"null","Tid":"0:37:55.0"},
{"Placering":2,"Namn":"magnusson, göran","Klubb/Ort":"Elfsborg","Startnr":"null","Tid":"0:40:24.0"},
{"Placering":3,"Namn":"höglund, bernt","Klubb/Ort":"Elfsborg","Startnr":"null","Tid":"0:41:40.0"},
{"Placering":4,"Namn":"andersson, jörgen","Klubb/Ort":"Elfsborg","Startnr":"null","Tid":"0:41:41.0"},
{"Placering":5,"Namn":"josefsson, jan","Klubb/Ort":"Elfsborg","Startnr":"null","Tid":"0:44:00.0"},
{"Placering":6,"Namn":"mikkola, kurt","Klubb/Ort":"Finland","Startnr":"null","Tid":"0:44:10.0"},
{"Placering":7,"Namn":"winlund, erik","Klubb/Ort":"Iggesund","Startnr":"null","Tid":"0:45:29.0"},
{"Placering":8,"Namn":"lindbäck, hilding","Klubb/Ort":"Luleå SS","Startnr":"null","Tid":"0:46:25.0"},
{"Placering":9,"Namn":"widell, jan","Klubb/Ort":"Hudiksvalls Simsällskap","Startnr":"null","Tid":"0:46:31.0"},
{"Placering":10,"Namn":"lisstorp, lars","Klubb/Ort":"Elfsborg","Startnr":"null","Tid":"0:46:49.0"},
{"Placering":11,"Namn":"raski, ero","Klubb/Ort":"Elfsborg","Startnr":"null","Tid":"0:47:16.0"},
{"Placering":12,"Namn":"särén, lars-åke","Klubb/Ort":"Elfsborg","Startnr":"null","Tid":"0:48:20.0"},
{"Placering":13,"Namn":"karlsson, lennart","Klubb/Ort":"SK Lore","Startnr":"null","Tid":"0:48:25.0"},
{"Placering":14,"Namn":"holm, tormod","Klubb/Ort":"Norge","Startnr":"null","Tid":"0:49:21.0"},
{"Placering":15,"Namn":"marcussén, arne","Klubb/Ort":"Danmark","Startnr":"null","Tid":"0:49:34.0"},
{"Placering":16,"Namn":"larsson, lars","Klubb/Ort":"Hudiksvalls Simsällskap","Startnr":"null","Tid":"0:51:21.0"},
{"Placering":17,"Namn":"bengtsson, bengt","Klubb/Ort":"Iggesund","Startnr":"null","Tid":"0:52:16.0"},
{"Placering":18,"Namn":"schröder, jan olof","Klubb/Ort":"IFK Grängesberg","Startnr":"null","Tid":"0:56:05.0"},
{"Placering":19,"Namn":"frans, jan","Klubb/Ort":"IFK Grängesberg","Startnr":"null","Tid":"0:57:50.0"},
{"Placering":20,"Namn":"montelius, ragnar","Klubb/Ort":"Gagnefs IF","Startnr":"null","Tid":"0:57:51.0"},
{"Placering":21,"Namn":"wallin, sven","Klubb/Ort":"Linköpings SS","Startnr":"null","Tid":"0:58:26.0"},
{"Placering":22,"Namn":"lindbom, björn","Klubb/Ort":"IFK Grängesberg","Startnr":"null","Tid":"0:59:17.0"},
{"Placering":23,"Namn":"pettersson, bengt arne","Klubb/Ort":"Hudiksvalls Simsällskap","Startnr":"null","Tid":"1:00:28.0"},
{"Placering":24,"Namn":"hultin, per","Klubb/Ort":"IFK Grängesberg","Startnr":"null","Tid":"1:00:32.0"},
{"Placering":25,"Namn":"meijer, tommy","Klubb/Ort":"Finspångs SS","Startnr":"null","Tid":"1:01:18.0"},
{"Placering":26,"Namn":"broberg, göte","Klubb/Ort":"Orsa IF","Startnr":"null","Tid":"1:02:50.0"},
{"Placering":27,"Namn":"larsson, lars","Klubb/Ort":"SK Lore","Startnr":"null","Tid":"1:03:25.0"},
{"Placering":28,"Namn":"holmgren, sören","Klubb/Ort":"SK Lore","Startnr":"null","Tid":"1:05:02.0"},
{"Placering":29,"Namn":"karlsson, tage","Klubb/Ort":"SK Lore","Startnr":"null","Tid":"1:05:41.0"},
{"Placering":30,"Namn":"montelius, erik","Klubb/Ort":"Gagnef IF","Startnr":"null","Tid":"1:05:55.0"},
{"Placering":30,"Namn":"thorné, mats","Klubb/Ort":"VAIK","Startnr":"null","Tid":"1:05:55.0"},
{"Placering":32,"Namn":"gustavsson, bo","Klubb/Ort":"SK Lore","Startnr":"null","Tid":"1:05:57.0"},
{"Placering":33,"Namn":"pettersson, björn","Klubb/Ort":"Linköpings Allmänna SS","Startnr":"null","Tid":"1:07:31.0"},
{"Placering":34,"Namn":"eriksson, stig","Klubb/Ort":"Lima IF","Startnr":"null","Tid":"1:14:45.0"},
{"Placering":35,"Namn":"modig, stig","Klubb/Ort":"VAIK","Startnr":"null","Tid":"1:24:36.0"}]